{
    "application": {
        "monthly_income": 50000,
        "employment_years": 5,
        "employment_type": "permanent",
        "debt_to_income": 0.30,
        "existing_loans": 1,
        "late_payment_count": 0,
        "credit_utilization": 0.35,
        "requested_amount": 300000,
        "loan_purpose": "car",
        "age": 35,
        "education_level": "bachelor",
        "marital_status": "married",
        "dependents": 2,
        "home_ownership": "own",
        "savings_balance": 250000,
        "checking_balance": 50000,
        "credit_history_length": 8,
        "previous_defaults": 0
    },
    "language": "th",
    "explanation_style": "formal"
}